rtl/addSubstractor.v
module addSubstractor(sub,A, B, out);
	input sub;
	input [7:0] A, B;
	output reg [8:0] out;
	
	always @(sub or A or B)
	begin
		if(sub)
			out = A - B;
		else
			out = A + B;
	end
endmodule

RAM.v
module RAM #(parameter RAM_LOCATIONS = 16, 	parameter RAM_BITS = 4)(input [RAM_BITS - 1:0] DATA_IN, input [4:0] ADDR, input WRITE, clk, output reg[RAM_BITS - 1:0] DATA_OUT);
	

	
	reg [RAM_BITS - 1: 0] RAM [RAM_LOCATIONS - 1:0];
		//Program to calculate the GCD of 2 numbers
	initial begin
		RAM[0]  = 8'b10000000;
		RAM[1]  = 8'b00111110;
		RAM[2]  = 8'b10000000;
		RAM[3]  = 8'b00111111;
		RAM[4]  = 8'b00011110;
		RAM[5]  = 8'b01111111;
		RAM[6]  = 8'b10110000;
		RAM[7]  = 8'b11001100;
		RAM[8]  = 8'b00011111;
		RAM[9]  = 8'b01111110;
		RAM[10] = 8'b00111111;
		RAM[11] = 8'b11000100;	
		RAM[12] = 8'b00011110;
		RAM[13] = 8'b01111111;
		RAM[14] = 8'b00111110;
		RAM[15] = 8'b11000100;
		RAM[16] = 8'b00011110;
		RAM[17] = 8'b11111111;
		RAM[30] = 8'b00000000;
		RAM[31] = 8'b00000000;
	end	
	
	/*
	initial 
	begin
	RAM[0] = 8'b10000000;
	RAM[1] = 8'b01111111;
	RAM[2] = 8'b10100100;
	RAM[3] = 8'b11000001;
	RAM[4] = 8'b11111111;
	RAM[31]= 8'b00000001;
	end
	*/
	always@(posedge clk)
	    if(WRITE)
			RAM[ADDR] <= DATA_IN;
		else
			DATA_OUT <= RAM[ADDR];
			
endmodule

rtl/DFF_reg.v
module DFF_reg	#(parameter size = 1)(Q, load, clear, clock, D);
	output reg [size -1 :0]Q;
	input clock, load, clear;
	input [size -1 :0]D;
	
always @ (posedge clock, negedge clear)
	 if(~clear)
		Q <= 0;
	 else if(load)	
		Q <= D;
	 else
		Q <= Q;
		
endmodule

mux4to1.v
module mux4to1 #(parameter size = 4)(input S0, S1, input [size - 1 : 0] i0, i1, i2, i3, output [size - 1 : 0] out);

assign out = (({S1, S0} == 2'b00) ? i0 :
			  ({S1, S0} == 2'b01) ? i1 :
			  ({S1, S0} == 2'b10) ? i2 :
			  i3);
			  

endmodule

rtl/mux2to1.v
module	mux2to1 #(parameter size = 2)(input S0, input[size - 1 :0] i1, i0, output [size - 1 :0] out);
		
	assign out = (S0 == 0)? i0 :i1 ;	
endmodule

DP.v
module DP(input IRload, JMPmux, PCload, Meminst, MemWr, Aload, Reset, Clock , Sub, 
		  input [1:0]Asel, input [7:0]INPUT ,output [7:0]OUTPUT,output [2:0]IR, output Aeq0, Apos);


wire [7:0] qIR, qA;
wire [4:0] qPC;

// output of reg/ connection wires

wire [7:0] qRAM;

wire [7:0] dIR, dA, dRAM;
wire [4:0] dPC; 

wire [1:0] wireNOR;
wire [4:0] wireJMP;
wire [7:0] wireAddSubRslt;
wire [7:0] wireMux4to1;
wire [1:0] wireAsel;

wire [4:0] address;

wire [8:0] resultAddSub;
wire [4:0] increment5bits;

/*High impedence for 4-to-1 mux*/
wire [7:0] Z;
assign Z = 8'bzzzzzzzz;
//assign 	wireJMP = JMPmux  ? qIR[4:0] :  qPC[4:0] + 5'b00001;
assign  increment5bits = qPC[4:0] + 5'b00001;
assign  wireAddSubRslt = resultAddSub;
assign  IR[2:0] = qIR[7:5];
assign  wireAsel = Asel;
assign  OUTPUT = qA;

or (wireNOR[0], qA[0], qA[1], qA[2], qA[3]);
or (wireNOR[1], qA[4], qA[5], qA[6], qA[7]);
nor (Aeq0, wireNOR[0], wireNOR[1]);

not	(Apos, qA[7]);


mux2to1	#(5)		muxJMP     (JMPmux, qIR[4:0], increment5bits, dPC);
mux2to1	#(5)		muxMeminst (Meminst, qIR[4:0], qPC, address);

mux4to1	#(8)		mux1    (Asel[0], Asel[1], wireAddSubRslt, INPUT, qRAM, Z, wireMux4to1);

DFF_reg #(8)		IRreg   (qIR, IRload, Reset, Clock, qRAM);
DFF_reg #(5)		PCreg   (qPC, PCload, Reset, Clock, dPC);
DFF_reg #(8)		Areg    (qA , Aload , Reset, Clock, wireMux4to1);
RAM		#(32, 8)	RAM32x8 (qA, address, MemWr, Clock, qRAM);

addSubstractor 		addSub1 (Sub, qA, qRAM, resultAddSub);



endmodule

DP_TB.v
module DP_tb();

    reg IRLoad, JMPmux, PCload, Meminst, MemWr, Aload, Reset, Clock, Sub;
    reg [1:0] Asel;
    reg [7:0] INPUT;

    wire Aeq0, Apos;
    wire [2:0] IR;
    wire [7:0] OUTPUT;

    DP inst1 (
        // Declare Input
        .IRload(IRLoad),
        .JMPmux(JMPmux),
        .PCload(PCload),
        .Meminst(Meminst),
        .MemWr(MemWr),
        .Aload(Aload),
        .Reset(Reset),
        .Clock(Clock),
        .Sub(Sub),
        .Asel(Asel),
        .INPUT(INPUT),

        // Declare output
        .Aeq0(Aeq0),
        .Apos(Apos),
        .IR(IR),
        .OUTPUT(OUTPUT)
    );

    // VCD generation
    initial begin
        $dumpfile("waveform.vcd");
        $dumpvars(0, DP_tb);
    end

    // Generate Clock
    initial begin
        Clock = 0;
        forever #5 Clock = ~Clock;
    end 


    // For Debug only..
    always @(posedge Clock) begin 
        $display("At time %t, IRLoad = %b", $time, IRLoad);
        $display("At time %t, Asel = %b", $time, Asel);
        $display("At time %t, INPUT = %b", $time, INPUT);

    end     
    
    task DP_init;
        begin
            // Intialize all inputs to be 0
            IRLoad = 1'b0;
            JMPmux = 1'b0;
            PCload = 1'b0; 
            Meminst = 1'b0;
            MemWr = 1'b0; 
            Aload = 1'b0; 
            Clock = 1'b0; 
            Sub = 1'b0;
            Reset = 1'b0;
            Asel = 2'b0;
            INPUT = 8'b0;
            #10; // Wait for the reset..

            // Figured out why the DFF is not loaded properly, was due to the
            // these Reset signals..
            Reset = 1'b1;  
            #10;
        end 
    endtask 

    task input_A;
        input [7:0] value;
        begin
            // INPUT A
            INPUT = value;
            {IRLoad, JMPmux, PCload, Meminst, MemWr, Aload, Sub} = 7'b0000010;
            Asel = 2'b01;
            #20;  // Wait two full clock cycles for the register to update
        end
    endtask

    task store_A;
        begin 
            Asel = 2'b00;
            {IRLoad, JMPmux, PCload, Meminst, MemWr, Aload, Sub} = 7'b0001100;
            #20;
        end 
    endtask

    task sub_A;
        begin 
            // SUB A in AReg with content in RAM specified by the instruction
            {IRLoad, JMPmux, PCload, Meminst, MemWr, Aload, Sub} = 7'b0000011;
            #10;    // Some delay else the AReg will be loaded with junk value..
            Asel = 2'b00;
            #20;
        end
    endtask 

    task add_A;
        begin 
            // ADD A in AReg with content in RAM specified by the instruction
            {IRLoad, JMPmux, PCload, Meminst, MemWr, Aload, Sub} = 7'b0000010;
            #10;    // Some delay else the AReg will be loaded with junk value..
            Asel = 2'b00;
            #20;
        end
    endtask 

    task fetch_decode;
        // Mimic fetch and decode cycle
        // we will send out the control signals accordingly...
        begin 
            // Fetch
            {IRLoad, JMPmux, PCload, Meminst, MemWr, Aload, Sub} = 7'b1010000;
            #10;
            // Decode
            {IRLoad, JMPmux, PCload, Meminst, MemWr, Aload, Sub} = 7'b0001000;
            #10;
        end 
    endtask

    task read_mem;
        // Read mememory by disabling MemWr
        // So that the data in RAM[x] will be at DATA_OUT
        begin
            MemWr = 1'b0;
            #10;
        end 
    endtask

    task jump_if_Aeq0;
        begin 
            Asel[1:0] = 2'b00;
            {IRLoad, JMPmux, Meminst, MemWr, Aload, Sub} = 6'b010000;
            PCload = Aeq0;
            #20;
        end 
    endtask 

    task jump_if_Apos;
        begin 
            Asel[1:0] = 2'b00;
            {IRLoad, JMPmux, Meminst, MemWr, Aload, Sub} = 6'b010000;
            PCload = Apos;
            #20;
        end 
    endtask 


    initial begin
        DP_init;
        // Test INPUT A and STORE A in RAM[0]
        /*
        input_A(8'd10);       
        store_A();   
        read_mem;
        */

        // Default RAM address = 0, since we didn't perform any
        // insturction fetch..
        // Load 8'd5 into RAM[0] first
        // Then Load 8'd10 into AReg
        // A = AReg input (8'd10)
        // B = RAM[0]
        // Only trigger Sub
        /*
        input_A(8'd5);       
        store_A();   
        read_mem;

        input_A(8'd10);
        sub_A;     
        */

        // Test ADD A
        // The steps is similar to previous test (SUB A)
        // Only deassert the "Sub".
        /*
        input_A(8'd10);       
        store_A();   
        read_mem;

        input_A(8'd100);
        add_A;     
        */
        
        // OK, now we're able to perform the INPUT, STORE, ADD, SUB operations
        // which is the main parts of the processor
        // Now we are going to test the Instruction Register (IR) and
        // Program Counter part of the DP.
        /*
        fetch_decode;
        fetch_decode;
        */

        // Last part, time to test the jumping mechanism 
        // EIther "Aeq0" or "Apos" will trigger the JMPmux to select "1"
        // which will be the change the PC counter value to be the 
        // address specified by the instructions
        fetch_decode;
        fetch_decode;
        jump_if_Aeq0;       // or use jump_if_Apos;
        $finish;
    end 

endmodule


   /*
        We're going to mimic the behavior of the actual program.
        Which required to simulated the Fetch=>Decode=>Execute cycle.

            RAM[0]  = 8'b10000000;	// IN A
            RAM[1]  = 8'b00111110;	// STORE A into address 11110
            RAM[2]  = 8'b10000000;	// IN A
            RAM[3]  = 8'b00111111;  // STORE A into address 11111
            RAM[4]  = 8'b00011110;	// LOAD Content of 11110 to A (Load first A to A)
            RAM[5]  = 8'b01111111;	// SUB A with Content of 11111 (First A - Second A)
            RAM[6]  = 8'b10110000;  // JUMP to 10000[0] if A equals 0
            RAM[7]  = 8'b11001100;  // JUMP to 01100[12] if A equals positive (First A > Second A)
            RAM[8]  = 8'b00011111;  // STORE A into address 11111
            RAM[9]  = 8'b01111110;	// SUB A with Content of 11110
            RAM[10] = 8'b00111111;  // STORE A into address 11111
            RAM[11] = 8'b11000100;	// JUMP to 01100 if A equals positive
            RAM[12] = 8'b00011110;  // STORE A into address 11110 (Store subtracted A back to original first A location)
            RAM[13] = 8'b01111111;	// SUB A with Content of 11111 (Second A - subtracted A)

            RAM[14] = 8'b00111110;  // STORE A into address 11110
            RAM[15] = 8'b11000100;	// JUMP to 00100 if A equals positive
            RAM[16] = 8'b00011110;	// LOAD Content of 11110 to A
            RAM[17] = 8'b11111111;  // HALT
            RAM[30] = 8'b00000000;
            RAM[31] = 8'b00000000;
        */

out/DP/waveform_A_from_input_value_100_add_RAM_addr_0_value_10_output_hex_6E.vcd
$date
	Sat Jun 17 13:17:15 2023
$end
$version
	Icarus Verilog
$end
$timescale
	1s
$end
$scope module DP_tb $end
$var wire 8 ! OUTPUT [7:0] $end
$var wire 3 " IR [2:0] $end
$var wire 1 # Apos $end
$var wire 1 $ Aeq0 $end
$var reg 1 % Aload $end
$var reg 2 & Asel [1:0] $end
$var reg 1 ' Clock $end
$var reg 8 ( INPUT [7:0] $end
$var reg 1 ) IRLoad $end
$var reg 1 * JMPmux $end
$var reg 1 + MemWr $end
$var reg 1 , Meminst $end
$var reg 1 - PCload $end
$var reg 1 . Reset $end
$var reg 1 / Sub $end
$scope module inst1 $end
$var wire 1 $ Aeq0 $end
$var wire 1 % Aload $end
$var wire 1 # Apos $end
$var wire 2 0 Asel [1:0] $end
$var wire 1 ' Clock $end
$var wire 8 1 INPUT [7:0] $end
$var wire 1 ) IRload $end
$var wire 1 * JMPmux $end
$var wire 1 + MemWr $end
$var wire 1 , Meminst $end
$var wire 8 2 OUTPUT [7:0] $end
$var wire 1 - PCload $end
$var wire 1 . Reset $end
$var wire 1 / Sub $end
$var wire 8 3 Z [7:0] $end
$var wire 2 4 wireAsel [1:0] $end
$var wire 2 5 wireNOR [1:0] $end
$var wire 8 6 wireMux4to1 [7:0] $end
$var wire 8 7 wireAddSubRslt [7:0] $end
$var wire 9 8 resultAddSub [8:0] $end
$var wire 8 9 qRAM [7:0] $end
$var wire 5 : qPC [4:0] $end
$var wire 8 ; qIR [7:0] $end
$var wire 8 < qA [7:0] $end
$var wire 5 = increment5bits [4:0] $end
$var wire 5 > dPC [4:0] $end
$var wire 5 ? address [4:0] $end
$var wire 3 @ IR [2:0] $end
$scope module Areg $end
$var wire 1 . clear $end
$var wire 1 ' clock $end
$var wire 1 % load $end
$var wire 8 A D [7:0] $end
$var parameter 32 B size $end
$var reg 8 C Q [7:0] $end
$upscope $end
$scope module IRreg $end
$var wire 1 . clear $end
$var wire 1 ' clock $end
$var wire 1 ) load $end
$var wire 8 D D [7:0] $end
$var parameter 32 E size $end
$var reg 8 F Q [7:0] $end
$upscope $end
$scope module PCreg $end
$var wire 1 . clear $end
$var wire 1 ' clock $end
$var wire 1 - load $end
$var wire 5 G D [4:0] $end
$var parameter 32 H size $end
$var reg 5 I Q [4:0] $end
$upscope $end
$scope module RAM32x8 $end
$var wire 8 J DATA_IN [7:0] $end
$var wire 1 + WRITE $end
$var wire 1 ' clk $end
$var wire 5 K ADDR [4:0] $end
$var parameter 32 L RAM_BITS $end
$var parameter 32 M RAM_LOCATIONS $end
$var reg 8 N DATA_OUT [7:0] $end
$upscope $end
$scope module addSub1 $end
$var wire 8 O A [7:0] $end
$var wire 8 P B [7:0] $end
$var wire 1 / sub $end
$var reg 9 Q out [8:0] $end
$upscope $end
$scope module mux1 $end
$var wire 1 R S0 $end
$var wire 1 S S1 $end
$var wire 8 T i0 [7:0] $end
$var wire 8 U i1 [7:0] $end
$var wire 8 V i2 [7:0] $end
$var wire 8 W i3 [7:0] $end
$var wire 8 X out [7:0] $end
$var parameter 32 Y size $end
$upscope $end
$scope module muxJMP $end
$var wire 1 * S0 $end
$var wire 5 Z i0 [4:0] $end
$var wire 5 [ i1 [4:0] $end
$var wire 5 \ out [4:0] $end
$var parameter 32 ] size $end
$upscope $end
$scope module muxMeminst $end
$var wire 1 , S0 $end
$var wire 5 ^ i0 [4:0] $end
$var wire 5 _ i1 [4:0] $end
$var wire 5 ` out [4:0] $end
$var parameter 32 a size $end
$upscope $end
$upscope $end
$scope task DP_init $end
$upscope $end
$scope task add_A $end
$upscope $end
$scope task fetch_decode $end
$upscope $end
$scope task input_A $end
$var reg 8 b value [7:0] $end
$upscope $end
$scope task read_mem $end
$upscope $end
$scope task store_A $end
$upscope $end
$scope task sub_A $end
$upscope $end
$upscope $end
$enddefinitions $end
$comment Show the parameter values. $end
$dumpall
b101 a
b101 ]
b1000 Y
b100000 M
b1000 L
b101 H
b1000 E
b1000 B
$end
#0
$dumpvars
bx b
b0 `
b0 _
b0 ^
b1 \
b0 [
b1 Z
bx X
bz W
bx V
b0 U
bx T
0S
0R
bx Q
bx P
b0 O
bx N
b0 K
b0 J
b0 I
b1 G
b0 F
bx D
b0 C
bx A
b0 @
b0 ?
b1 >
b1 =
b0 <
b0 ;
b0 :
bx 9
bx 8
bx 7
bx 6
b0 5
b0 4
bz 3
b0 2
b0 1
b0 0
0/
0.
0-
0,
0+
0*
0)
b0 (
0'
b0 &
0%
1$
1#
b0 "
b0 !
$end
#5
b10000000 6
b10000000 A
b10000000 X
b10000000 7
b10000000 T
b10000000 8
b10000000 Q
b10000000 9
b10000000 D
b10000000 N
b10000000 P
b10000000 V
1'
#10
0'
1.
#15
1'
#20
b1010 6
b1010 A
b1010 X
1R
0'
b1 4
b1 &
b1 0
1%
b1010 (
b1010 1
b1010 U
b1010 b
#25
0$
b10001010 7
b10001010 T
b1 5
b10001010 8
b10001010 Q
b1010 !
b1010 2
b1010 <
b1010 C
b1010 J
b1010 O
1'
#30
0'
#35
1'
#40
b10001010 6
b10001010 A
b10001010 X
0R
0'
1,
1+
0%
b0 4
b0 &
b0 0
#45
1'
#50
0'
#55
1'
#60
0'
0+
#65
b10100 6
b10100 A
b10100 X
b10100 7
b10100 T
b10100 8
b10100 Q
b1010 9
b1010 D
b1010 N
b1010 P
b1010 V
1'
#70
b1100100 6
b1100100 A
b1100100 X
1R
0'
b1 4
b1 &
b1 0
0,
1%
b1100100 (
b1100100 1
b1100100 U
b1100100 b
#75
b1101110 7
b1101110 T
b11 5
b1101110 8
b1101110 Q
b1100100 !
b1100100 2
b1100100 <
b1100100 C
b1100100 J
b1100100 O
1'
#80
0'
#85
1'
#90
0'
#95
1'
#100
b1101110 6
b1101110 A
b1101110 X
0R
0'
b0 4
b0 &
b0 0
#105
b1111000 6
b1111000 A
b1111000 X
b1111000 7
b1111000 T
b1111000 8
b1111000 Q
b1101110 !
b1101110 2
b1101110 <
b1101110 C
b1101110 J
b1101110 O
1'
#110
0'
#115
b10000010 6
b10000010 A
b10000010 X
b10000010 7
b10000010 T
b10000010 8
b10000010 Q
b1111000 !
b1111000 2
b1111000 <
b1111000 C
b1111000 J
b1111000 O
1'
