rtl/addSubstractor.v
module addSubstractor(sub,A, B, out);
	input sub;
	input [7:0] A, B;
	output reg [8:0] out;
	
	always @(sub or A or B)
	begin
		if(sub)
			out = A - B;
		else
			out = A + B;
	end
endmodule

RAM.v
module RAM #(parameter RAM_LOCATIONS = 16, 	parameter RAM_BITS = 4)(input [RAM_BITS - 1:0] DATA_IN, input [4:0] ADDR, input WRITE, clk, output reg[RAM_BITS - 1:0] DATA_OUT);
	

	
	reg [RAM_BITS - 1: 0] RAM [RAM_LOCATIONS - 1:0];
		//Program to calculate the GCD of 2 numbers
	initial begin
		RAM[0]  = 8'b10000000;
		RAM[1]  = 8'b00111110;
		RAM[2]  = 8'b10000000;
		RAM[3]  = 8'b00111111;
		RAM[4]  = 8'b00011110;
		RAM[5]  = 8'b01111111;
		RAM[6]  = 8'b10110000;
		RAM[7]  = 8'b11001100;
		RAM[8]  = 8'b00011111;
		RAM[9]  = 8'b01111110;
		RAM[10] = 8'b00111111;
		RAM[11] = 8'b11000100;	
		RAM[12] = 8'b00011110;
		RAM[13] = 8'b01111111;
		RAM[14] = 8'b00111110;
		RAM[15] = 8'b11000100;
		RAM[16] = 8'b00011110;
		RAM[17] = 8'b11111111;
		RAM[30] = 8'b00000000;
		RAM[31] = 8'b00000000;
	end	
	
	/*
	initial 
	begin
	RAM[0] = 8'b10000000;
	RAM[1] = 8'b01111111;
	RAM[2] = 8'b10100100;
	RAM[3] = 8'b11000001;
	RAM[4] = 8'b11111111;
	RAM[31]= 8'b00000001;
	end
	*/
	always@(posedge clk)
	    if(WRITE)
			RAM[ADDR] <= DATA_IN;
		else
			DATA_OUT <= RAM[ADDR];
			
endmodule

rtl/DFF_reg.v
module DFF_reg	#(parameter size = 1)(Q, load, clear, clock, D);
	output reg [size -1 :0]Q;
	input clock, load, clear;
	input [size -1 :0]D;
	
always @ (posedge clock, negedge clear)
	 if(~clear)
		Q <= 0;
	 else if(load)	
		Q <= D;
	 else
		Q <= Q;
		
endmodule

mux4to1.v
module mux4to1 #(parameter size = 4)(input S0, S1, input [size - 1 : 0] i0, i1, i2, i3, output [size - 1 : 0] out);

assign out = (({S1, S0} == 2'b00) ? i0 :
			  ({S1, S0} == 2'b01) ? i1 :
			  ({S1, S0} == 2'b10) ? i2 :
			  i3);
			  

endmodule

rtl/mux2to1.v
module	mux2to1 #(parameter size = 2)(input S0, input[size - 1 :0] i1, i0, output [size - 1 :0] out);
		
	assign out = (S0 == 0)? i0 :i1 ;	
endmodule

DP.v
module DP(input IRload, JMPmux, PCload, Meminst, MemWr, Aload, Reset, Clock , Sub, 
		  input [1:0]Asel, input [7:0]INPUT ,output [7:0]OUTPUT,output [2:0]IR, output Aeq0, Apos);


wire [7:0] qIR, qA;
wire [4:0] qPC;

// output of reg/ connection wires

wire [7:0] qRAM;

wire [7:0] dIR, dA, dRAM;
wire [4:0] dPC; 

wire [1:0] wireNOR;
wire [4:0] wireJMP;
wire [7:0] wireAddSubRslt;
wire [7:0] wireMux4to1;
wire [1:0] wireAsel;

wire [4:0] address;

wire [8:0] resultAddSub;
wire [4:0] increment5bits;

/*High impedence for 4-to-1 mux*/
wire [7:0] Z;
assign Z = 8'bzzzzzzzz;
//assign 	wireJMP = JMPmux  ? qIR[4:0] :  qPC[4:0] + 5'b00001;
assign  increment5bits = qPC[4:0] + 5'b00001;
assign  wireAddSubRslt = resultAddSub;
assign  IR[2:0] = qIR[7:5];
assign  wireAsel = Asel;
assign  OUTPUT = qA;

or (wireNOR[0], qA[0], qA[1], qA[2], qA[3]);
or (wireNOR[1], qA[4], qA[5], qA[6], qA[7]);
nor (Aeq0, wireNOR[0], wireNOR[1]);

not	(Apos, qA[7]);


mux2to1	#(5)		muxJMP     (JMPmux, qIR[4:0], increment5bits, dPC);
mux2to1	#(5)		muxMeminst (Meminst, qIR[4:0], qPC, address);

mux4to1	#(8)		mux1    (Asel[0], Asel[1], wireAddSubRslt, INPUT, qRAM, Z, wireMux4to1);

DFF_reg #(8)		IRreg   (qIR, IRload, Reset, Clock, qRAM);
DFF_reg #(5)		PCreg   (qPC, PCload, Reset, Clock, dPC);
DFF_reg #(8)		Areg    (qA , Aload , Reset, Clock, wireMux4to1);
RAM		#(32, 8)	RAM32x8 (qA, address, MemWr, Clock, qRAM);

addSubstractor 		addSub1 (Sub, qA, qRAM, resultAddSub);



endmodule

CU.v
module CU(output reg IRload, JMPmux, PCload, Meminst, MemWr, Aload, Sub, Halt,
		  output reg[1:0] Asel,
		  input clock, reset, Enter, Aeq0, Apos,
		  input [2:0]IR
		  );

reg [3:0] state, nextState;

// Define states with readable names
parameter start = 4'b0000, fetch = 4'b0001, decode = 4'b0010, 
		  load = 4'b1000, store = 4'b1001, add = 4'b1010, sub = 4'b1011,
		  Input = 4'b1100, jz = 4'b1101, jpos = 4'b1110, halt = 4'b1111;


// State transition block  
always @(posedge clock, negedge reset)
begin
	if(~reset)
	state <= start;	// Reset state to start if reset signal is active
	else
	state <= nextState;	// GO to next state
end


always @(state, Enter, IR)
	case (state)
	start	: begin
			  {IRload, JMPmux, PCload, Meminst, MemWr, Aload, Sub} = 7'b0000000;			  
			  Asel[1:0] = 2'b00;
			  Halt = 1'b0;
			  nextState = fetch;
			  end
			  
	fetch	: begin
			  {IRload, JMPmux, PCload, Meminst, MemWr, Aload, Sub} = 7'b1010000;
			  Asel[1:0] = 2'b00;
			  Halt = 1'b0;	
			  nextState = decode;
			  end
	
	decode	:begin
			{IRload, JMPmux, PCload, Meminst, MemWr, Aload, Sub} = 7'b00001000; 
			Asel[1:0] = 2'b00;
			Halt = 1'b0;
				case (IR)
					3'b000 :	nextState = load;	
					3'b001 :	nextState = store;	
					3'b010 :	nextState = add;				
					3'b011 :	nextState = sub;		
					3'b100 :	nextState = Input;								
					3'b101 :	nextState = jz;					
					3'b110 :	nextState = jpos;
					3'b111 :	nextState = halt;			
					default :	nextState = decode;							
				endcase
			end
	load	: begin
			  Halt = 1'b0;
			  Asel[1:0] = 2'b10;
			  {IRload, JMPmux, PCload, Meminst, MemWr, Aload, Sub} = 7'b0000010;
			  nextState = start;
			  end		
	
	store	: begin
			  Halt = 1'b0;
			  Asel[1:0] = 2'b00;
			  {IRload, JMPmux, PCload, Meminst, MemWr, Aload, Sub} = 7'b0001100;
			  nextState = start;
			  end	
			  
	add		: begin
			  Halt = 1'b0;
			  Asel[1:0] = 2'b00;
			  {IRload, JMPmux, PCload, Meminst, MemWr, Aload, Sub} = 7'b0000010;
			  nextState = start;
			  end	
			  
	sub		: begin
			  Halt = 1'b0;
			  Asel[1:0] = 2'b00;
			  {IRload, JMPmux, PCload, Meminst, MemWr, Aload, Sub} = 7'b0000011;
			  nextState = start;
			  end	
			  	
	Input	: begin
			  Halt = 1'b0;
			  Asel[1:0] = 2'b01;
			  {IRload, JMPmux, PCload, Meminst, MemWr, Aload, Sub} = 7'b0000010;
			  if(~Enter)
				nextState = Input;
			  else
				nextState = start;
			  end
			  	
	jz		: begin
			  Halt = 1'b0;
			  Asel[1:0] = 2'b00;
			  {IRload, JMPmux, Meminst, MemWr, Aload, Sub} = 6'b010000;
			  PCload = Aeq0;
			  nextState = start;
			  end	
			  
	jpos	: begin
			  Halt = 1'b0;
			  Asel[1:0] = 2'b00;
			  {IRload, JMPmux, Meminst, MemWr, Aload, Sub} = 6'b010000;
			  PCload = Apos;
			  nextState = start;
			  end	
			  
	halt	: begin
			  Halt = 1'b1;
			  Asel[1:0] = 2'b00;
			  {IRload, JMPmux, PCload, Meminst, MemWr, Aload, Sub} = 7'b0000000;
			  nextState = halt;
			  end		  
	endcase
			  			  			  			  			  		  			  			  								
endmodule

CombinedCUnDP.v
module CombinedCUnDP(input [7:0]dataIn, input clock, input reset, input enter, output [7:0]dataOut, output Halt, output wire [2:0]IR);

wire IRload, JMPmux, PCload, Meminst, MemWr, Aload, Sub, Aeq0, Apos;
wire [1:0] Asel;

CU controlUnit(IRload, JMPmux, PCload, Meminst, MemWr, Aload, Sub, Halt, Asel,
		  clock, reset, enter, Aeq0, Apos,
		  IR
		  );
		  
DP dataPath(IRload, JMPmux, PCload, Meminst, MemWr, Aload, reset, clock , Sub, 
		  Asel, dataIn, dataOut ,IR, Aeq0, Apos);

endmodule

CombinedCUnDP_TB.v
// This is the fully integrated top module of the processor
module CombinedCUnDP_tb();

    reg clock, reset, enter;
    reg [7:0] dataIn;

    wire Halt;
    wire [2:0] IR;
    wire [7:0] dataOut;

    integer X, Y;


    CombinedCUnDP microprocessor(
        // INPUT
        .dataIn(dataIn),
        .clock(clock),
        .reset(reset),
        .enter(enter),

        // OUTPUT
        .Halt(Halt),
        .IR(IR),
        .dataOut(dataOut)
    );

    // Init Clock
    initial begin
        clock = 0;
        forever #5 clock = ~clock;
    end 

    // VCD generation
    initial begin
        $dumpfile("waveform.vcd");
        $dumpvars(0, CombinedCUnDP_tb);
    end


    task trigger_reset; 
        begin
            reset = 0; // reset signal starts low
            #10; 
            reset = 1; // set reset high
        end
    endtask

    task processor_init;
        begin 
            enter <= 0; // enter signal starts low
            dataIn <= 8'd0; // input data starts as 0
        end 
    endtask


    // Monitor halt signal and display GCD when halt is high
    always @ (Halt) begin
        if(Halt) begin
            $display("THE GCD OF %d(X) & %d(Y) is: %d \n", X, Y, dataOut);
            $finish;
        end 
    end



    
    initial begin
        X = 8'd51;
        Y = 8'd22;

        processor_init;
        trigger_reset;

        dataIn = X; 
        $display("INPUT FOR X: %d\n", dataIn); 
        #30 enter = 1; // set enter high to indicate dataIn is ready
        #30 enter = 0; 

        dataIn = Y; 
        $display("INPUT FOR Y: %d\n", dataIn); 
        #30 enter = 1; // set enter high to indicate dataIn is ready
        #30 enter = 0; 

    end 

        // Simulate input of X and Y values
        /*
	initial
        begin
            processor_init;
            trigger_reset;
            #12 dataIn = 8'd50; // 12 time units in, set dataIn as 50 (X value)
            $display("INPUT FOR X: %d\n", dataIn); 
            X = dataIn;     
            #10 enter = 1; // 10 time units later, set enter high to indicate dataIn is ready
            #4 enter = 0; // 4 time units later, set enter back to low
            #26 dataIn = 8'd17; // 26 time units later, set dataIn as 17 (Y value)
            $display("INPUT FOR Y: %d\n", dataIn);
            Y = dataIn;
            #10 enter = 1; // 10 time units later, set enter high
            #4 enter = 0; // 4 time units later, set enter back to low
        end*/

endmodule

out/CombinedCUnDP/waveform.vcd
$date
	Sat Jun 17 14:48:54 2023
$end
$version
	Icarus Verilog
$end
$timescale
	1s
$end
$scope module CombinedCUnDP_tb $end
$var wire 8 ! dataOut [7:0] $end
$var wire 3 " IR [2:0] $end
$var wire 1 # Halt $end
$var reg 1 $ clock $end
$var reg 8 % dataIn [7:0] $end
$var reg 1 & enter $end
$var reg 1 ' reset $end
$var integer 32 ( X [31:0] $end
$var integer 32 ) Y [31:0] $end
$scope module microprocessor $end
$var wire 1 $ clock $end
$var wire 8 * dataIn [7:0] $end
$var wire 1 & enter $end
$var wire 1 ' reset $end
$var wire 8 + dataOut [7:0] $end
$var wire 1 , Sub $end
$var wire 1 - PCload $end
$var wire 1 . Meminst $end
$var wire 1 / MemWr $end
$var wire 1 0 JMPmux $end
$var wire 1 1 IRload $end
$var wire 3 2 IR [2:0] $end
$var wire 1 # Halt $end
$var wire 2 3 Asel [1:0] $end
$var wire 1 4 Apos $end
$var wire 1 5 Aload $end
$var wire 1 6 Aeq0 $end
$scope module controlUnit $end
$var wire 1 & Enter $end
$var wire 1 $ clock $end
$var wire 1 ' reset $end
$var wire 3 7 IR [2:0] $end
$var wire 1 4 Apos $end
$var wire 1 6 Aeq0 $end
$var parameter 4 8 Input $end
$var parameter 4 9 add $end
$var parameter 4 : decode $end
$var parameter 4 ; fetch $end
$var parameter 4 < halt $end
$var parameter 4 = jpos $end
$var parameter 4 > jz $end
$var parameter 4 ? load $end
$var parameter 4 @ start $end
$var parameter 4 A store $end
$var parameter 4 B sub $end
$var reg 1 5 Aload $end
$var reg 2 C Asel [1:0] $end
$var reg 1 # Halt $end
$var reg 1 1 IRload $end
$var reg 1 0 JMPmux $end
$var reg 1 / MemWr $end
$var reg 1 . Meminst $end
$var reg 1 - PCload $end
$var reg 1 , Sub $end
$var reg 4 D nextState [3:0] $end
$var reg 4 E state [3:0] $end
$upscope $end
$scope module dataPath $end
$var wire 1 6 Aeq0 $end
$var wire 1 5 Aload $end
$var wire 1 4 Apos $end
$var wire 2 F Asel [1:0] $end
$var wire 1 $ Clock $end
$var wire 8 G INPUT [7:0] $end
$var wire 1 1 IRload $end
$var wire 1 0 JMPmux $end
$var wire 1 / MemWr $end
$var wire 1 . Meminst $end
$var wire 8 H OUTPUT [7:0] $end
$var wire 1 - PCload $end
$var wire 1 ' Reset $end
$var wire 1 , Sub $end
$var wire 8 I Z [7:0] $end
$var wire 2 J wireAsel [1:0] $end
$var wire 2 K wireNOR [1:0] $end
$var wire 8 L wireMux4to1 [7:0] $end
$var wire 8 M wireAddSubRslt [7:0] $end
$var wire 9 N resultAddSub [8:0] $end
$var wire 8 O qRAM [7:0] $end
$var wire 5 P qPC [4:0] $end
$var wire 8 Q qIR [7:0] $end
$var wire 8 R qA [7:0] $end
$var wire 5 S increment5bits [4:0] $end
$var wire 5 T dPC [4:0] $end
$var wire 5 U address [4:0] $end
$var wire 3 V IR [2:0] $end
$scope module Areg $end
$var wire 1 ' clear $end
$var wire 1 $ clock $end
$var wire 1 5 load $end
$var wire 8 W D [7:0] $end
$var parameter 32 X size $end
$var reg 8 Y Q [7:0] $end
$upscope $end
$scope module IRreg $end
$var wire 1 ' clear $end
$var wire 1 $ clock $end
$var wire 1 1 load $end
$var wire 8 Z D [7:0] $end
$var parameter 32 [ size $end
$var reg 8 \ Q [7:0] $end
$upscope $end
$scope module PCreg $end
$var wire 1 ' clear $end
$var wire 1 $ clock $end
$var wire 1 - load $end
$var wire 5 ] D [4:0] $end
$var parameter 32 ^ size $end
$var reg 5 _ Q [4:0] $end
$upscope $end
$scope module RAM32x8 $end
$var wire 8 ` DATA_IN [7:0] $end
$var wire 1 / WRITE $end
$var wire 1 $ clk $end
$var wire 5 a ADDR [4:0] $end
$var parameter 32 b RAM_BITS $end
$var parameter 32 c RAM_LOCATIONS $end
$var reg 8 d DATA_OUT [7:0] $end
$upscope $end
$scope module addSub1 $end
$var wire 8 e A [7:0] $end
$var wire 8 f B [7:0] $end
$var wire 1 , sub $end
$var reg 9 g out [8:0] $end
$upscope $end
$scope module mux1 $end
$var wire 1 h S0 $end
$var wire 1 i S1 $end
$var wire 8 j i0 [7:0] $end
$var wire 8 k i1 [7:0] $end
$var wire 8 l i2 [7:0] $end
$var wire 8 m i3 [7:0] $end
$var wire 8 n out [7:0] $end
$var parameter 32 o size $end
$upscope $end
$scope module muxJMP $end
$var wire 1 0 S0 $end
$var wire 5 p i0 [4:0] $end
$var wire 5 q i1 [4:0] $end
$var wire 5 r out [4:0] $end
$var parameter 32 s size $end
$upscope $end
$scope module muxMeminst $end
$var wire 1 . S0 $end
$var wire 5 t i0 [4:0] $end
$var wire 5 u i1 [4:0] $end
$var wire 5 v out [4:0] $end
$var parameter 32 w size $end
$upscope $end
$upscope $end
$upscope $end
$scope task processor_init $end
$upscope $end
$scope task trigger_reset $end
$upscope $end
$upscope $end
$enddefinitions $end
$comment Show the parameter values. $end
$dumpall
b101 w
b101 s
b1000 o
b100000 c
b1000 b
b101 ^
b1000 [
b1000 X
b1011 B
b1001 A
b0 @
b1000 ?
b1101 >
b1110 =
b1111 <
b1 ;
b10 :
b1010 9
b1100 8
$end
#0
$dumpvars
b0 v
b0 u
b0 t
b1 r
b0 q
b1 p
bx n
bz m
bx l
b0 k
bx j
0i
0h
bx g
bx f
b0 e
bx d
b0 a
b0 `
b0 _
b1 ]
b0 \
bx Z
b0 Y
bx W
b0 V
b0 U
b1 T
b1 S
b0 R
b0 Q
b0 P
bx O
bx N
bx M
bx L
b0 K
b0 J
bz I
b0 H
b0 G
b0 F
b0 E
b1 D
b0 C
b0 7
16
05
14
b0 3
b0 2
01
00
0/
0.
0-
0,
b0 +
b0 *
b10110 )
b110011 (
0'
0&
b0 %
0$
0#
b0 "
b0 !
$end
#5
b10000000 L
b10000000 W
b10000000 n
b10000000 M
b10000000 j
b10000000 N
b10000000 g
b10000000 O
b10000000 Z
b10000000 d
b10000000 f
b10000000 l
1$
#10
0$
b110011 %
b110011 *
b110011 G
b110011 k
1'
#15
b10 D
11
1-
b1 E
1$
#20
0$
#25
b10 T
b10 ]
b10 r
b100 "
b100 2
b100 7
b100 V
b1100 D
01
0-
1.
b10 S
b10 p
b1 P
b1 _
b1 t
b10000000 Q
b10000000 \
b10 E
1$
#30
0$
#35
b110011 L
b110011 W
b110011 n
b1 U
b1 a
b1 v
1h
0.
15
b1 J
b1 3
b1 C
b1 F
b1100 E
1$
#40
b0 D
0$
1&
#45
06
b1110001 L
b1110001 W
b1110001 n
b11 K
0h
b1110001 M
b1110001 j
b1 D
b0 J
b0 3
b0 C
b0 F
05
b1110001 N
b1110001 g
b110011 !
b110011 +
b110011 H
b110011 R
b110011 Y
b110011 `
b110011 e
b0 E
b111110 O
b111110 Z
b111110 d
b111110 f
b111110 l
1$
#50
0$
#55
b10 D
11
1-
b1 E
1$
#60
0$
#65
b11110 U
b11110 a
b11110 v
b11 T
b11 ]
b11 r
b11110 u
b11110 q
b1 "
b1 2
b1 7
b1 V
b1001 D
01
0-
1.
b11 S
b11 p
b10 P
b10 _
b10 t
b111110 Q
b111110 \
b10 E
1$
#70
0$
b10110 %
b10110 *
b10110 G
b10110 k
0&
#75
b110011 L
b110011 W
b110011 n
b110011 M
b110011 j
b0 D
1/
b110011 N
b110011 g
b1001 E
b0 O
b0 Z
b0 d
b0 f
b0 l
1$
#80
0$
#85
b10 U
b10 a
b10 v
b1 D
0.
0/
b0 E
1$
#90
0$
#95
b10110011 L
b10110011 W
b10110011 n
b10110011 M
b10110011 j
b10 D
11
1-
b10110011 N
b10110011 g
b1 E
b10000000 O
b10000000 Z
b10000000 d
b10000000 f
b10000000 l
1$
#100
0$
1&
#105
b0 U
b0 a
b0 v
b100 T
b100 ]
b100 r
b0 u
b0 q
b100 "
b100 2
b100 7
b100 V
b1100 D
01
0-
1.
b100 S
b100 p
b11 P
b11 _
b11 t
b10000000 Q
b10000000 \
b10 E
1$
#110
0$
#115
b10110 L
b10110 W
b10110 n
b11 U
b11 a
b11 v
1h
b0 D
0.
15
b1 J
b1 3
b1 C
b1 F
b1100 E
1$
#120
0$
#125
b1010101 L
b1010101 W
b1010101 n
0h
b1010101 M
b1010101 j
b1 D
b0 J
b0 3
b0 C
b0 F
05
b1010101 N
b1010101 g
b10110 !
b10110 +
b10110 H
b10110 R
b10110 Y
b10110 `
b10110 e
b0 E
b111111 O
b111111 Z
b111111 d
b111111 f
b111111 l
1$
#130
0$
0&
#135
b10 D
11
1-
b1 E
1$
#140
0$
#145
b11111 U
b11111 a
b11111 v
b101 T
b101 ]
b101 r
b11111 u
b11111 q
b1 "
b1 2
b1 7
b1 V
b1001 D
01
0-
1.
b101 S
b101 p
b100 P
b100 _
b100 t
b111111 Q
b111111 \
b10 E
1$
#150
0$
#155
b10110 L
b10110 W
b10110 n
b10110 M
b10110 j
b0 D
1/
b10110 N
b10110 g
b1001 E
b0 O
b0 Z
b0 d
b0 f
b0 l
1$
#160
0$
#165
b100 U
b100 a
b100 v
b1 D
0.
0/
b0 E
1$
#170
0$
#175
b110100 L
b110100 W
b110100 n
b110100 M
b110100 j
b10 D
11
1-
b110100 N
b110100 g
b1 E
b11110 O
b11110 Z
b11110 d
b11110 f
b11110 l
1$
#180
0$
#185
b11110 U
b11110 a
b11110 v
b110 T
b110 ]
b110 r
b11110 u
b11110 q
b0 "
b0 2
b0 7
b0 V
b1000 D
01
0-
1.
b110 S
b110 p
b101 P
b101 _
b101 t
b11110 Q
b11110 \
b10 E
1$
#190
0$
#195
b110011 L
b110011 W
b110011 n
b101 U
b101 a
b101 v
1i
b1001001 M
b1001001 j
b0 D
0.
15
b10 J
b10 3
b10 C
b10 F
b1001001 N
b1001001 g
b1000 E
b110011 O
b110011 Z
b110011 d
b110011 f
b110011 l
1$
#200
0$
#205
b10110010 L
b10110010 W
b10110010 n
0i
b10110010 M
b10110010 j
b1 D
b0 J
b0 3
b0 C
b0 F
05
b10110010 N
b10110010 g
b110011 !
b110011 +
b110011 H
b110011 R
b110011 Y
b110011 `
b110011 e
b0 E
b1111111 O
b1111111 Z
b1111111 d
b1111111 f
b1111111 l
1$
#210
0$
#215
b10 D
11
1-
b1 E
1$
#220
0$
#225
b11111 U
b11111 a
b11111 v
b111 T
b111 ]
b111 r
b11111 u
b11111 q
b11 "
b11 2
b11 7
b11 V
b1011 D
01
0-
1.
b111 S
b111 p
b110 P
b110 _
b110 t
b1111111 Q
b1111111 \
b10 E
1$
#230
0$
#235
b11101 L
b11101 W
b11101 n
b110 U
b110 a
b110 v
b11101 M
b11101 j
b0 D
0.
15
1,
b11101 N
b11101 g
b1011 E
b10110 O
b10110 Z
b10110 d
b10110 f
b10110 l
1$
#240
0$
#245
b11001101 L
b11001101 W
b11001101 n
b11001101 M
b11001101 j
b1 D
05
0,
b11001101 N
b11001101 g
b11101 !
b11101 +
b11101 H
b11101 R
b11101 Y
b11101 `
b11101 e
b0 E
b10110000 O
b10110000 Z
b10110000 d
b10110000 f
b10110000 l
1$
#250
0$
#255
b10 D
11
1-
b1 E
1$
#260
0$
#265
b10000 U
b10000 a
b10000 v
b1000 T
b1000 ]
b1000 r
b10000 u
b10000 q
b101 "
b101 2
b101 7
b101 V
b1101 D
01
0-
1.
b1000 S
b1000 p
b111 P
b111 _
b111 t
b10110000 Q
b10110000 \
b10 E
1$
#270
0$
#275
b111011 L
b111011 W
b111011 n
b10000 T
b10000 ]
b10000 r
b111 U
b111 a
b111 v
b111011 M
b111011 j
b0 D
10
0.
b111011 N
b111011 g
b1101 E
b11110 O
b11110 Z
b11110 d
b11110 f
b11110 l
1$
#280
0$
#285
b11101001 L
b11101001 W
b11101001 n
b1000 T
b1000 ]
b1000 r
b11101001 M
b11101001 j
b1 D
00
b11101001 N
b11101001 g
b0 E
b11001100 O
b11001100 Z
b11001100 d
b11001100 f
b11001100 l
1$
#290
0$
#295
b10 D
11
1-
b1 E
1$
#300
0$
#305
b1100 U
b1100 a
b1100 v
b1001 T
b1001 ]
b1001 r
b1100 u
b1100 q
b110 "
b110 2
b110 7
b110 V
b1110 D
01
0-
1.
b1001 S
b1001 p
b1000 P
b1000 _
b1000 t
b11001100 Q
b11001100 \
b10 E
1$
#310
0$
#315
b111011 L
b111011 W
b111011 n
b1100 T
b1100 ]
b1100 r
b1000 U
b1000 a
b1000 v
b111011 M
b111011 j
b0 D
1-
10
0.
b111011 N
b111011 g
b1110 E
b11110 O
b11110 Z
b11110 d
b11110 f
b11110 l
1$
#320
0$
#325
b111100 L
b111100 W
b111100 n
b1101 T
b1101 ]
b1101 r
b111100 M
b111100 j
b1100 U
b1100 a
b1100 v
b1 D
00
0-
b111100 N
b111100 g
b1101 S
b1101 p
b1100 P
b1100 _
b1100 t
b0 E
b11111 O
b11111 Z
b11111 d
b11111 f
b11111 l
1$
#330
0$
#335
b111011 L
b111011 W
b111011 n
b111011 M
b111011 j
b10 D
11
1-
b111011 N
b111011 g
b1 E
b11110 O
b11110 Z
b11110 d
b11110 f
b11110 l
1$
#340
0$
#345
b11110 U
b11110 a
b11110 v
b1110 T
b1110 ]
b1110 r
b11110 u
b11110 q
b0 "
b0 2
b0 7
b0 V
b1000 D
01
0-
1.
b1110 S
b1110 p
b1101 P
b1101 _
b1101 t
b11110 Q
b11110 \
b10 E
1$
#350
0$
#355
b110011 L
b110011 W
b110011 n
b1101 U
b1101 a
b1101 v
1i
b1010000 M
b1010000 j
b0 D
0.
15
b10 J
b10 3
b10 C
b10 F
b1010000 N
b1010000 g
b1000 E
b110011 O
b110011 Z
b110011 d
b110011 f
b110011 l
1$
#360
0$
#365
b10110010 L
b10110010 W
b10110010 n
0i
b10110010 M
b10110010 j
b1 D
b0 J
b0 3
b0 C
b0 F
05
b10110010 N
b10110010 g
b110011 !
b110011 +
b110011 H
b110011 R
b110011 Y
b110011 `
b110011 e
b0 E
b1111111 O
b1111111 Z
b1111111 d
b1111111 f
b1111111 l
1$
#370
0$
#375
b10 D
11
1-
b1 E
1$
#380
0$
#385
b11111 U
b11111 a
b11111 v
b1111 T
b1111 ]
b1111 r
b11111 u
b11111 q
b11 "
b11 2
b11 7
b11 V
b1011 D
01
0-
1.
b1111 S
b1111 p
b1110 P
b1110 _
b1110 t
b1111111 Q
b1111111 \
b10 E
1$
#390
0$
#395
b11101 L
b11101 W
b11101 n
b1110 U
b1110 a
b1110 v
b11101 M
b11101 j
b0 D
0.
15
1,
b11101 N
b11101 g
b1011 E
b10110 O
b10110 Z
b10110 d
b10110 f
b10110 l
1$
#400
0$
#405
b1011011 L
b1011011 W
b1011011 n
b1011011 M
b1011011 j
b1 D
05
0,
b1011011 N
b1011011 g
b11101 !
b11101 +
b11101 H
b11101 R
b11101 Y
b11101 `
b11101 e
b0 E
b111110 O
b111110 Z
b111110 d
b111110 f
b111110 l
1$
#410
0$
#415
b10 D
11
1-
b1 E
1$
#420
0$
#425
b11110 U
b11110 a
b11110 v
b10000 T
b10000 ]
b10000 r
b11110 u
b11110 q
b1 "
b1 2
b1 7
b1 V
b1001 D
01
0-
1.
b10000 S
b10000 p
b1111 P
b1111 _
b1111 t
b111110 Q
b111110 \
b10 E
1$
#430
0$
#435
b1010000 L
b1010000 W
b1010000 n
b1010000 M
b1010000 j
b0 D
1/
b1010000 N
b1010000 g
b1001 E
b110011 O
b110011 Z
b110011 d
b110011 f
b110011 l
1$
#440
0$
#445
b1111 U
b1111 a
b1111 v
b1 D
0.
0/
b0 E
1$
#450
0$
#455
b11100001 L
b11100001 W
b11100001 n
b11100001 M
b11100001 j
b10 D
11
1-
b11100001 N
b11100001 g
b1 E
b11000100 O
b11000100 Z
b11000100 d
b11000100 f
b11000100 l
1$
#460
0$
#465
b100 U
b100 a
b100 v
b10001 T
b10001 ]
b10001 r
b100 u
b100 q
b110 "
b110 2
b110 7
b110 V
b1110 D
01
0-
1.
b10001 S
b10001 p
b10000 P
b10000 _
b10000 t
b11000100 Q
b11000100 \
b10 E
1$
#470
0$
#475
b111011 L
b111011 W
b111011 n
b100 T
b100 ]
b100 r
b10000 U
b10000 a
b10000 v
b111011 M
b111011 j
b0 D
1-
10
0.
b111011 N
b111011 g
b1110 E
b11110 O
b11110 Z
b11110 d
b11110 f
b11110 l
1$
#480
0$
#485
b101 T
b101 ]
b101 r
b100 U
b100 a
b100 v
b1 D
00
0-
b101 S
b101 p
b100 P
b100 _
b100 t
b0 E
1$
#490
0$
#495
b10 D
11
1-
b1 E
1$
#500
0$
#505
b11110 U
b11110 a
b11110 v
b110 T
b110 ]
b110 r
b11110 u
b11110 q
b0 "
b0 2
b0 7
b0 V
b1000 D
01
0-
1.
b110 S
b110 p
b101 P
b101 _
b101 t
b11110 Q
b11110 \
b10 E
1$
#510
0$
#515
b11101 L
b11101 W
b11101 n
b101 U
b101 a
b101 v
1i
b111010 M
b111010 j
b0 D
0.
15
b10 J
b10 3
b10 C
b10 F
b111010 N
b111010 g
b1000 E
b11101 O
b11101 Z
b11101 d
b11101 f
b11101 l
1$
#520
0$
#525
b10011100 L
b10011100 W
b10011100 n
0i
b10011100 M
b10011100 j
b1 D
b0 J
b0 3
b0 C
b0 F
05
b10011100 N
b10011100 g
b0 E
b1111111 O
b1111111 Z
b1111111 d
b1111111 f
b1111111 l
1$
#530
0$
#535
b10 D
11
1-
b1 E
1$
#540
0$
#545
b11111 U
b11111 a
b11111 v
b111 T
b111 ]
b111 r
b11111 u
b11111 q
b11 "
b11 2
b11 7
b11 V
b1011 D
01
0-
1.
b111 S
b111 p
b110 P
b110 _
b110 t
b1111111 Q
b1111111 \
b10 E
1$
#550
0$
#555
b111 L
b111 W
b111 n
b110 U
b110 a
b110 v
b111 M
b111 j
b0 D
0.
15
1,
b111 N
b111 g
b1011 E
b10110 O
b10110 Z
b10110 d
b10110 f
b10110 l
1$
#560
0$
#565
b10110111 L
b10110111 W
b10110111 n
b1 K
b10110111 M
b10110111 j
b1 D
05
0,
b10110111 N
b10110111 g
b111 !
b111 +
b111 H
b111 R
b111 Y
b111 `
b111 e
b0 E
b10110000 O
b10110000 Z
b10110000 d
b10110000 f
b10110000 l
1$
#570
0$
#575
b10 D
11
1-
b1 E
1$
#580
0$
#585
b10000 U
b10000 a
b10000 v
b1000 T
b1000 ]
b1000 r
b10000 u
b10000 q
b101 "
b101 2
b101 7
b101 V
b1101 D
01
0-
1.
b1000 S
b1000 p
b111 P
b111 _
b111 t
b10110000 Q
b10110000 \
b10 E
1$
#590
0$
#595
b100101 L
b100101 W
b100101 n
b10000 T
b10000 ]
b10000 r
b111 U
b111 a
b111 v
b100101 M
b100101 j
b0 D
10
0.
b100101 N
b100101 g
b1101 E
b11110 O
b11110 Z
b11110 d
b11110 f
b11110 l
1$
#600
0$
#605
b11010011 L
b11010011 W
b11010011 n
b1000 T
b1000 ]
b1000 r
b11010011 M
b11010011 j
b1 D
00
b11010011 N
b11010011 g
b0 E
b11001100 O
b11001100 Z
b11001100 d
b11001100 f
b11001100 l
1$
#610
0$
#615
b10 D
11
1-
b1 E
1$
#620
0$
#625
b1100 U
b1100 a
b1100 v
b1001 T
b1001 ]
b1001 r
b1100 u
b1100 q
b110 "
b110 2
b110 7
b110 V
b1110 D
01
0-
1.
b1001 S
b1001 p
b1000 P
b1000 _
b1000 t
b11001100 Q
b11001100 \
b10 E
1$
#630
0$
