CU.v
module CU(
	output reg IRload, JMPmux, PCload, Meminst, MemWr, Aload, Sub, Halt,
	output reg [1:0] Asel,
	input clock, reset, Enter, Aeq0, Apos,
	input [2:0] IR
);

reg [3:0] state, nextState;

// Define states with readable names
parameter start = 4'b0000, fetch = 4'b0001, decode = 4'b0010, 
		  load = 4'b1000, store = 4'b1001, add = 4'b1010, sub = 4'b1011,
		  Input = 4'b1100, jz = 4'b1101, jpos = 4'b1110, halt = 4'b1111;


// State transition block  
always @(posedge clock, negedge reset)
begin
	if(~reset)
	state <= start;	// Reset state to start if reset signal is active
	else
	state <= nextState;	// GO to next state
end


always @(state, Enter, IR)
	case (state)
	start	: begin
			  {IRload, JMPmux, PCload, Meminst, MemWr, Aload, Sub} = 7'b0000000;			  
			  Asel[1:0] = 2'b00;
			  Halt = 1'b0;
			  nextState = fetch;
			  end
			  
	fetch	: begin
			  {IRload, JMPmux, PCload, Meminst, MemWr, Aload, Sub} = 7'b1010000;
			  Asel[1:0] = 2'b00;
			  Halt = 1'b0;	
			  nextState = decode;
			  end
	
	decode	:begin
			{IRload, JMPmux, PCload, Meminst, MemWr, Aload, Sub} = 7'b00001000; 
			Asel[1:0] = 2'b00;
			Halt = 1'b0;
				case (IR)
					3'b000 :	nextState = load;	
					3'b001 :	nextState = store;	
					3'b010 :	nextState = add;				
					3'b011 :	nextState = sub;		
					3'b100 :	nextState = Input;								
					3'b101 :	nextState = jz;					
					3'b110 :	nextState = jpos;
					3'b111 :	nextState = halt;			
					default :	nextState = decode;							
				endcase
			end
	load	: begin
			  Halt = 1'b0;
			  Asel[1:0] = 2'b10;
			  {IRload, JMPmux, PCload, Meminst, MemWr, Aload, Sub} = 7'b0000010;
			  nextState = start;
			  end		
	
	store	: begin
			  Halt = 1'b0;
			  Asel[1:0] = 2'b00;
			  {IRload, JMPmux, PCload, Meminst, MemWr, Aload, Sub} = 7'b0001100;
			  nextState = start;
			  end	
			  
	add		: begin
			  Halt = 1'b0;
			  Asel[1:0] = 2'b00;
			  {IRload, JMPmux, PCload, Meminst, MemWr, Aload, Sub} = 7'b0000010;
			  nextState = start;
			  end	
			  
	sub		: begin
			  Halt = 1'b0;
			  Asel[1:0] = 2'b00;
			  {IRload, JMPmux, PCload, Meminst, MemWr, Aload, Sub} = 7'b0000011;
			  nextState = start;
			  end	
			  	
	Input	: begin
			  Halt = 1'b0;
			  Asel[1:0] = 2'b01;
			  {IRload, JMPmux, PCload, Meminst, MemWr, Aload, Sub} = 7'b0000010;
			  if(~Enter)
				nextState = Input;
			  else
				nextState = start;
			  end
			  	
	jz		: begin
			  Halt = 1'b0;
			  Asel[1:0] = 2'b00;
			  {IRload, JMPmux, Meminst, MemWr, Aload, Sub} = 6'b010000;
			  PCload = Aeq0;
			  nextState = start;
			  end	
			  
	jpos	: begin
			  Halt = 1'b0;
			  Asel[1:0] = 2'b00;
			  {IRload, JMPmux, Meminst, MemWr, Aload, Sub} = 6'b010000;
			  PCload = Apos;
			  nextState = start;
			  end	
			  
	halt	: begin
			  Halt = 1'b1;
			  Asel[1:0] = 2'b00;
			  {IRload, JMPmux, PCload, Meminst, MemWr, Aload, Sub} = 7'b0000000;
			  nextState = halt;
			  end		  
	endcase
			  			  			  			  			  		  			  			  								
endmodule

testbench/rtl_tb/CU_TB.v
module CU_tb();

    reg clock, reset, Enter, Aeq0, Apos;
    reg [2:0] IR;

    wire IRLoad, JMPmux, PCload, Meminst, MemWr, Aload, Sub, Halt;
    wire [1:0] Asel;

    CU inst1(
        // Output
        .IRload(IRLoad),
        .JMPmux(JMPmux),
        .PCload(PCload),
        .Meminst(Meminst),
        .MemWr(MemWr),
        .Aload(Aload),
        .Sub(Sub),
        .Halt(Halt),
        .Asel(Asel),

        // Input
        .clock(clock),
        .reset(reset),
        .Enter(Enter),
        .Aeq0(Aeq0),
        .Apos(Apos),
        .IR(IR)
    );

    // For Debug only..
    always @(posedge clock)
        $display("At time %t, IRLoad = %b", $time, IRLoad);

    // VCD generation
    initial begin
        $dumpfile("waveform.vcd");
        $dumpvars(0, CU_tb);
    end

    initial begin
        clock = 0;
        forever #5 clock = ~clock;
    end 


    initial begin
        // This should init all input to 0 at state "start"
        // Reset=0, we should at start state
        Enter = 0;
        reset = 0;
        #10;

        // Remove the reset and wait awhile
        // At next rising edge, we should be at fetch state
        reset = 1;
        #10;

        // Now we should be at decode state, for next rising edge
        // Lets make it goto "load" state by setting [2:0] IR = 3'b000
        #10;
        IR[2:0] = 3'b000;
        #10;

        // After this time should be "start"
        #10;
        // After this will be "fetch" state
        #10;

        // Now we should be at decode state, for next rising edge
        // Lets make it goto "store" state by setting [2:0] IR = 3'b001
        #10;
        IR[2:0] = 3'b001;
        #10;

        // After this time should be "start"
        #10;
        // After this will be "fetch" state
        #10;

        // Now we should be at decode state, for next rising edge
        // Lets make it goto "input" state by setting [2:0] IR = 3'b100
        #10;
        IR[2:0] = 3'b100;
        Enter = 1;      // Needed to transition to next state, else it will keep at the same state
        #10;

        // After this time should be "start"
        #10;
        Enter = 0;      // Reset Enter
        // After this will be "fetch" state
        #10;

        // Now we should be at decode state, for next rising edge
        // Lets make it goto "add" state by setting [2:0] IR = 3'b010
        #10;
        IR[2:0] = 3'b010;
        #10;

        // After this time should be "start"
        #10;
        // After this will be "fetch" state
        #10;

        // Now we should be at decode state, for next rising edge
        // Lets make it goto "sub" state by setting [2:0] IR = 3'b011
        #10;
        IR[2:0] = 3'b011;
        #10;

        // After this time should be "start"
        #10;
        // After this will be "fetch" state
        #10;

        // Now we should be at decode state, for next rising edge
        // Lets make it goto "jz" state by setting [2:0] IR = 3'b101
        #10;
        IR[2:0] = 3'b101;
        #10;

        // After this time should be "start"
        #10;
        // After this will be "fetch" state
        #10;

        // Now we should be at decode state, for next rising edge
        // Lets make it goto "jpos" state by setting [2:0] IR = 3'b110
        #10;
        IR[2:0] = 3'b110;
        #10;


        // After this time should be "start"
        #10;
        // After this will be "fetch" state
        #10;

        // Now we should be at decode state, for next rising edge
        // Lets make it goto "halt" state by setting [2:0] IR = 3'b111
        #10;
        IR[2:0] = 3'b111;
        #10;

        // We should be back to "start" state by now
        reset = 0;
        #10;

        $finish;
    end 
endmodule

out/CU/waveform.vcd
$date
	Fri Jun 16 14:19:50 2023
$end
$version
	Icarus Verilog
$end
$timescale
	1s
$end
$scope module CU_tb $end
$var wire 1 ! Sub $end
$var wire 1 " PCload $end
$var wire 1 # Meminst $end
$var wire 1 $ MemWr $end
$var wire 1 % JMPmux $end
$var wire 1 & IRLoad $end
$var wire 1 ' Halt $end
$var wire 2 ( Asel [1:0] $end
$var wire 1 ) Aload $end
$var reg 1 * Aeq0 $end
$var reg 1 + Apos $end
$var reg 1 , Enter $end
$var reg 3 - IR [2:0] $end
$var reg 1 . clock $end
$var reg 1 / reset $end
$scope module inst1 $end
$var wire 1 * Aeq0 $end
$var wire 1 + Apos $end
$var wire 1 , Enter $end
$var wire 3 0 IR [2:0] $end
$var wire 1 . clock $end
$var wire 1 / reset $end
$var parameter 4 1 Input $end
$var parameter 4 2 add $end
$var parameter 4 3 decode $end
$var parameter 4 4 fetch $end
$var parameter 4 5 halt $end
$var parameter 4 6 jpos $end
$var parameter 4 7 jz $end
$var parameter 4 8 load $end
$var parameter 4 9 start $end
$var parameter 4 : store $end
$var parameter 4 ; sub $end
$var reg 1 ) Aload $end
$var reg 2 < Asel [1:0] $end
$var reg 1 ' Halt $end
$var reg 1 & IRload $end
$var reg 1 % JMPmux $end
$var reg 1 $ MemWr $end
$var reg 1 # Meminst $end
$var reg 1 " PCload $end
$var reg 1 ! Sub $end
$var reg 4 = nextState [3:0] $end
$var reg 4 > state [3:0] $end
$upscope $end
$upscope $end
$enddefinitions $end
$comment Show the parameter values. $end
$dumpall
b1011 ;
b1001 :
b0 9
b1000 8
b1101 7
b1110 6
b1111 5
b1 4
b10 3
b1010 2
b1100 1
$end
#0
$dumpvars
b0 >
b1 =
b0 <
bx 0
0/
0.
bx -
0,
x+
x*
0)
b0 (
0'
0&
0%
0$
0#
0"
0!
$end
#5
1.
#10
0.
1/
#15
b10 =
1&
1"
b1 >
1.
#20
0.
#25
0&
0"
1#
b10 >
1.
#30
b1000 =
0.
b0 -
b0 0
#35
b0 =
0#
1)
b10 (
b10 <
b1000 >
1.
#40
0.
#45
b1 =
b0 (
b0 <
0)
b0 >
1.
#50
0.
#55
b10 =
1&
1"
b1 >
1.
#60
0.
#65
b1000 =
0&
0"
1#
b10 >
1.
#70
b1001 =
0.
b1 -
b1 0
#75
b0 =
1$
b1001 >
1.
#80
0.
#85
b1 =
0#
0$
b0 >
1.
#90
0.
#95
b10 =
1&
1"
b1 >
1.
#100
0.
#105
b1001 =
0&
0"
1#
b10 >
1.
#110
b1100 =
0.
1,
b100 -
b100 0
#115
b0 =
0#
1)
b1 (
b1 <
b1100 >
1.
#120
0.
#125
b1 =
b0 (
b0 <
0)
b0 >
1.
#130
0.
0,
#135
b10 =
1&
1"
b1 >
1.
#140
0.
#145
b1100 =
0&
0"
1#
b10 >
1.
#150
b1010 =
0.
b10 -
b10 0
#155
b0 =
0#
1)
b1010 >
1.
#160
0.
#165
b1 =
0)
b0 >
1.
#170
0.
#175
b10 =
1&
1"
b1 >
1.
#180
0.
#185
b1010 =
0&
0"
1#
b10 >
1.
#190
b1011 =
0.
b11 -
b11 0
#195
b0 =
0#
1)
1!
b1011 >
1.
#200
0.
#205
b1 =
0)
0!
b0 >
1.
#210
0.
#215
b10 =
1&
1"
b1 >
1.
#220
0.
#225
b1011 =
0&
0"
1#
b10 >
1.
#230
b1101 =
0.
b101 -
b101 0
#235
b0 =
x"
1%
0#
b1101 >
1.
#240
0.
#245
b1 =
0%
0"
b0 >
1.
#250
0.
#255
b10 =
1&
1"
b1 >
1.
#260
0.
#265
b1101 =
0&
0"
1#
b10 >
1.
#270
b1110 =
0.
b110 -
b110 0
#275
b0 =
x"
1%
0#
b1110 >
1.
#280
0.
#285
b1 =
0%
0"
b0 >
1.
#290
0.
#295
b10 =
1&
1"
b1 >
1.
#300
0.
#305
b1110 =
0&
0"
1#
b10 >
1.
#310
b1111 =
0.
b111 -
b111 0
#315
0#
1'
b1111 >
1.
#320
b1 =
0'
b0 >
0.
0/
