RAM.v
module RAM #(parameter RAM_LOCATIONS = 32, 	parameter RAM_BITS = 8)(input [RAM_BITS - 1:0] DATA_IN, input [4:0] ADDR, input WRITE, clk, output reg[RAM_BITS - 1:0] DATA_OUT);
	

	
	reg [RAM_BITS - 1: 0] RAM [RAM_LOCATIONS - 1:0];
		//Program to calculate the GCD of 2 numbers
	initial begin
		RAM[0]  = 8'b10000000;	// IN A
		RAM[1]  = 8'b00111110;	// STORE A into address 11110
		RAM[2]  = 8'b10000000;	// IN A
		RAM[3]  = 8'b00111111;  // STORE A into address 11111
		RAM[4]  = 8'b00011110;	// LOAD Content of 11110 to A (Load first A to A)
		RAM[5]  = 8'b01111111;	// SUB A with Content of 11111 (First A - Second A)
		RAM[6]  = 8'b10110000;  // JUMP to 10000[0] if A equals 0
		RAM[7]  = 8'b11001100;  // JUMP to 01100[12] if A equals positive (First A > Second A)
		RAM[8]  = 8'b00011111;  // STORE A into address 11111
		RAM[9]  = 8'b01111110;	// SUB A with Content of 11110
		RAM[10] = 8'b00111111;  // STORE A into address 11111
		RAM[11] = 8'b11000100;	// JUMP to 01100 if A equals positive
		RAM[12] = 8'b00011110;  // STORE A into address 11110 (Store subtracted A back to original first A location)
		RAM[13] = 8'b01111111;	// SUB A with Content of 11111 (Second A - subtracted A)

		RAM[14] = 8'b00111110;  // STORE A into address 11110
		RAM[15] = 8'b11000100;	// JUMP to 00100 if A equals positive
		RAM[16] = 8'b00011110;	// LOAD Content of 11110 to A
		RAM[17] = 8'b11111111;  // HALT
		RAM[30] = 8'b00000000;
		RAM[31] = 8'b00000000;
	end	
	
	// PC Count	: Instruction code: Desc
	//  00000	: 100 00000; -- INPUT A
	//  00001	: 001 11110; -- STORE A -> 11110
	//  00010	: 100 00000; -- INPUT A
	//  00011	: 001 11111; -- STORE A -> 11111
	//  00100	: 000 11110; -- LOAD (11110) -> A
	//  00101	: 011 11111; -- A = A - (11111)
	//  00110	: 101 10000; -- JUMP to PC (10000) if A = 0
	//  00111	: 110 01100; -- JUMP to PC (01100) if A = +ve
	//	01000	: 000 11111; -- STORE A -> 11111
	//  01001	: 011 11110; -- A = A - (11110)  
	//  01010	: 001 11111; -- STORE A -> 11111
	//  01011	: 110 00100; -- JUMP to PC (01100) if A = +ve
	//  01100	: 000 11110; -- STORE A -> 11110
	//  01101	: 011 11111; -- A = A - 11111
	//  01110   : 001 11110; -- STORE A -> 11110
	//  01111   : 110 00100; -- JUMP to PC (00100) if A = +ve
	//  10000	: 000 11110; -- LOAD (11110) -> A
	//  10001	: 111 11111; -- HALT    
	   
	/*	Exampel from Lab Manual
	initial 
	begin
	RAM[0] = 8'b10000000; -- INPUT A
	RAM[1] = 8'b01111111; -- A = A - (11111)
	RAM[2] = 8'b10100100; -- JUMP to PC (00100) if A = 0
	RAM[3] = 8'b11000001; -- JUMP to PC (00001) if A = +ve
	RAM[4] = 8'b11111111; -- HALT
	RAM[31]= 8'b00000001; -- CONSTANT 1
	end
	*/
	always@(posedge clk)
	    if(WRITE)
			RAM[ADDR] <= DATA_IN;
		else
			DATA_OUT <= RAM[ADDR];
			
endmodule

testbench/rtl_tb/RAM_TB.v
module RAM_tb();

    parameter RAM_LOCATIONS = 32;
    parameter RAM_BITS = 8;

    reg [RAM_BITS-1:0]  DATA_IN;
    reg [4:0] ADDR;
    reg WRITE;
    reg clk;

    wire [RAM_BITS-1:0] DATA_OUT;

    RAM #(RAM_LOCATIONS, RAM_BITS) inst1 (
        .DATA_IN(DATA_IN),
        .ADDR(ADDR),
        .WRITE(WRITE),
        .clk(clk),
        .DATA_OUT(DATA_OUT)
    );

    // Clock generator
    initial clk = 0;
    always #5 clk = ~clk;  // 10s clock period

    // VCD generation
    initial begin
        $dumpfile("waveform.vcd");
        $dumpvars(0, RAM_tb);
    end

    initial begin
        // Init, at the same time, it read RAM[0] which is
        // 8'b10000000 = 0x80
        DATA_IN = 0;
        ADDR = 0;
        WRITE = 0;
        #10;

        // Read RAM[1] which will be 8'b00111110 (0x3E);
        // Just so happen similar as init statements, LOL
        // Init statement will read RAM[0]
        DATA_IN = 0;
        ADDR = 5'd1;
        WRITE = 0;
        #10;

        // Write RAM[31] with value 8'b10101010 (0xAA)
        DATA_IN = 8'b10101010;
        ADDR = 5'd31;
        WRITE = 1;
        #10;

        // Reset WRITE to ensure that we are no longer in write mode
        WRITE = 0;
        #10;

        // Read Back RAM[31] to see if write success expect (0xAA)
        DATA_IN = 0;
        ADDR = 5'd31;
        WRITE = 0;
        #10;

        // Need to add these statements else stuck at 
        // vvp.exe RAM_TB_out
        // VCD info: dumpfile waveform.vcd opened for output.
        #10;  // Some delay to see the last instruction effect on the waveform
        $finish;  // Stops the simulation
    end 

endmodule

out/RAM/waveform.vcd
$date
	Thu Jun 15 22:02:39 2023
$end
$version
	Icarus Verilog
$end
$timescale
	1s
$end
$scope module RAM_tb $end
$var wire 8 ! DATA_OUT [7:0] $end
$var parameter 32 " RAM_BITS $end
$var parameter 32 # RAM_LOCATIONS $end
$var reg 5 $ ADDR [4:0] $end
$var reg 8 % DATA_IN [7:0] $end
$var reg 1 & WRITE $end
$var reg 1 ' clk $end
$scope module inst1 $end
$var wire 5 ( ADDR [4:0] $end
$var wire 8 ) DATA_IN [7:0] $end
$var wire 1 & WRITE $end
$var wire 1 ' clk $end
$var parameter 32 * RAM_BITS $end
$var parameter 32 + RAM_LOCATIONS $end
$var reg 8 , DATA_OUT [7:0] $end
$upscope $end
$upscope $end
$enddefinitions $end
$comment Show the parameter values. $end
$dumpall
b100000 +
b1000 *
b100000 #
b1000 "
$end
#0
$dumpvars
bx ,
b0 )
b0 (
0'
0&
b0 %
b0 $
bx !
$end
#5
b10000000 !
b10000000 ,
1'
#10
0'
b1 $
b1 (
#15
b111110 !
b111110 ,
1'
#20
0'
1&
b11111 $
b11111 (
b10101010 %
b10101010 )
#25
1'
#30
0'
0&
#35
b10101010 !
b10101010 ,
1'
#40
0'
b0 %
b0 )
